examples/__init__.py
examples/app_request_test.py
examples/app_response_test.py
examples/request_sender_test.py
pf_flask_rest_com/__init__.py
pf_flask_rest_com/api_def.py
pf_flask_rest_com/pf_flask_request_helper.py
pf_flask_rest_com/pf_flask_response_helper.py
pf_flask_rest_com/common/__init__.py
pf_flask_rest_com/common/pf_flask_rest_com_const.py
pf_flask_rest_com/common/pffr_exception.py
pf_flask_rest_com/data/__init__.py
pf_flask_rest_com/data/pffrc_response_data.py
pf_flask_rest_com/data/pffrc_response_status.py
pf_flask_rest_com/schema/__init__.py
pf_flask_rest_com/schema/pffrc_response_schema.py
pf_flask_rest_com/schema/pffrc_schema_helper.py
PF_Flask_Rest_Com-1.0.2.dist-info/LICENSE
PF_Flask_Rest_Com-1.0.2.dist-info/METADATA
PF_Flask_Rest_Com-1.0.2.dist-info/WHEEL
PF_Flask_Rest_Com-1.0.2.dist-info/top_level.txt
PF_Flask_Rest_Com-1.0.2.dist-info/RECORD
