Metadata-Version: 2.1
Name: PF-Flask-Rest-Com
Version: 1.0.2
Summary: Flask REST API Common Implementation by Problem Fighter Library
Home-page: https://github.com/problemfighter/pf-flask-rest-com
Author: Problem Fighter
Author-email: problemfighter.com@gmail.com
License: Apache 2.0
Platform: any
Classifier: Environment :: Web Environment
Classifier: Intended Audience :: Developers
Classifier: License :: OSI Approved :: Apache Software License
Classifier: Operating System :: OS Independent
Classifier: Programming Language :: Python
Classifier: Topic :: Internet :: WWW/HTTP :: Dynamic Content
Classifier: Topic :: Software Development :: Libraries :: Python Modules
License-File: LICENSE
Requires-Dist: Flask
Requires-Dist: Marshmallow
Requires-Dist: PF-PY-Common
